{
  "name": "simple",
  "version": "1.0.0",
  "author": "KNOV Team",
  "description": "Minimal purple test theme - Home & Settings only",
  "views": {
    "home": ["default"],
    "settings": ["default"],
    "fileview": ["default"],
    "fileedit": ["default"],
    "search": ["default"],
    "overview": ["default"],
    "dashboard": ["default"],
    "admin": ["default"],
    "playground": ["default"],
    "history": ["default"],
    "latestchanges": ["default"],
    "browsefiles": ["default"]
  },
  "features": {
    "darkMode": true,
    "colorSchemes": [{ "name": "default", "label": "Purple Theme" }]
  }
}
